autocrud/__init__.py
autocrud/types.py
autocrud/cli/__init__.py
autocrud/cli/__main__.py
autocrud/cli/build.py
autocrud/cli/config.py
autocrud/crud/__init__.py
autocrud/crud/core.py
autocrud/crud/route_templates/__init__.py
autocrud/crud/route_templates/basic.py
autocrud/crud/route_templates/blob.py
autocrud/crud/route_templates/create.py
autocrud/crud/route_templates/delete.py
autocrud/crud/route_templates/get.py
autocrud/crud/route_templates/graphql.py
autocrud/crud/route_templates/migrate.py
autocrud/crud/route_templates/patch.py
autocrud/crud/route_templates/search.py
autocrud/crud/route_templates/switch.py
autocrud/crud/route_templates/update.py
autocrud/message_queue/__init__.py
autocrud/message_queue/basic.py
autocrud/message_queue/rabbitmq.py
autocrud/message_queue/simple.py
autocrud/permission/__init__.py
autocrud/permission/acl.py
autocrud/permission/action.py
autocrud/permission/basic.py
autocrud/permission/composite.py
autocrud/permission/data_based.py
autocrud/permission/meta_based.py
autocrud/permission/rbac.py
autocrud/permission/simple.py
autocrud/resource_manager/__init__.py
autocrud/resource_manager/basic.py
autocrud/resource_manager/binary_processor.py
autocrud/resource_manager/core.py
autocrud/resource_manager/data_converter.py
autocrud/resource_manager/events.py
autocrud/resource_manager/partial.py
autocrud/resource_manager/permission.py
autocrud/resource_manager/storage_factory.py
autocrud/resource_manager/blob_store/__init__.py
autocrud/resource_manager/blob_store/s3.py
autocrud/resource_manager/blob_store/simple.py
autocrud/resource_manager/meta_store/__init__.py
autocrud/resource_manager/meta_store/df.py
autocrud/resource_manager/meta_store/fast_slow.py
autocrud/resource_manager/meta_store/postgres.py
autocrud/resource_manager/meta_store/redis.py
autocrud/resource_manager/meta_store/simple.py
autocrud/resource_manager/meta_store/sqlite3.py
autocrud/resource_manager/resource_store/__init__.py
autocrud/resource_manager/resource_store/cache.py
autocrud-0.7.4.dist-info/METADATA
autocrud-0.7.4.dist-info/WHEEL
autocrud-0.7.4.dist-info/licenses/LICENSE
autocrud-0.7.4.dist-info/RECORD
