Metadata-Version: 2.4
Name: autocrud
Version: 0.7.4
Summary: 自動產生 CRUD API 的 Python 函式庫
Project-URL: Homepage, https://github.com/HYChou0515/autocrud
Project-URL: Documentation, https://HYChou0515.github.io/autocrud/
Project-URL: Repository, https://github.com/HYChou0515/autocrud.git
Project-URL: Issues, https://github.com/HYChou0515/autocrud/issues
Author-email: HYChou0515 <hychou.svm@example.com>
License: MIT License
License-File: LICENSE
Keywords: api,automation,crud,fastapi,rest
Classifier: Development Status :: 4 - Beta
Classifier: Framework :: FastAPI
Classifier: Intended Audience :: Developers
Classifier: License :: OSI Approved :: MIT License
Classifier: Operating System :: OS Independent
Classifier: Programming Language :: Python :: 3
Classifier: Programming Language :: Python :: 3.11
Classifier: Programming Language :: Python :: 3.12
Classifier: Programming Language :: Python :: 3.13
Classifier: Topic :: Internet :: WWW/HTTP :: HTTP Servers
Classifier: Topic :: Software Development :: Libraries :: Python Modules
Requires-Python: >=3.11
Requires-Dist: fastapi>=0.116.1
Requires-Dist: jsonpatch>=1.33
Requires-Dist: jsonpointer>=3.0.0
Requires-Dist: more-itertools>=10.7.0
Requires-Dist: msgpack>=1.1.1
Requires-Dist: msgspec>=0.19.0
Requires-Dist: pydantic>=2.11.7
Requires-Dist: qqabc>=0.2.1
Requires-Dist: strawberry-graphql>=0.288.1
Requires-Dist: xxhash>=3.5.0
Provides-Extra: cli
Requires-Dist: datamodel-code-generator[http]>=0.35.0; extra == 'cli'
Requires-Dist: fstui>=0.1.1; extra == 'cli'
Requires-Dist: httpx>=0.28.1; extra == 'cli'
Requires-Dist: tenacity>=9.1.2; extra == 'cli'
Requires-Dist: textual>=6.3.0; extra == 'cli'
Requires-Dist: typer>=0.20.0; extra == 'cli'
Provides-Extra: dev
Requires-Dist: boto3>=1.40.21; extra == 'dev'
Requires-Dist: coverage>=7.9.2; extra == 'dev'
Requires-Dist: furo>=2025.7.19; extra == 'dev'
Requires-Dist: linkify-it-py>=2.0.3; extra == 'dev'
Requires-Dist: myst-parser>=4.0.1; extra == 'dev'
Requires-Dist: pytest-asyncio>=1.1.0; extra == 'dev'
Requires-Dist: pytest>=8.4.1; extra == 'dev'
Requires-Dist: python-magic>=0.4.27; extra == 'dev'
Requires-Dist: ruff>=0.12.4; extra == 'dev'
Requires-Dist: sphinx-autodoc-typehints>=3.2.0; extra == 'dev'
Requires-Dist: sphinx-design>=0.6.1; extra == 'dev'
Requires-Dist: sphinx-termynal>=0.2.1; extra == 'dev'
Requires-Dist: sphinx>=8.2.3; extra == 'dev'
Requires-Dist: sphinxcontrib-mermaid>=1.2.3; extra == 'dev'
Provides-Extra: docs
Requires-Dist: boto3>=1.40.21; extra == 'docs'
Requires-Dist: furo>=2025.7.19; extra == 'docs'
Requires-Dist: linkify-it-py>=2.0.3; extra == 'docs'
Requires-Dist: myst-parser>=4.0.1; extra == 'docs'
Requires-Dist: sphinx-autodoc-typehints>=3.2.0; extra == 'docs'
Requires-Dist: sphinx-design>=0.6.1; extra == 'docs'
Requires-Dist: sphinx-termynal>=0.2.1; extra == 'docs'
Requires-Dist: sphinx>=8.2.3; extra == 'docs'
Requires-Dist: sphinxcontrib-mermaid>=1.2.3; extra == 'docs'
Provides-Extra: magic
Requires-Dist: python-magic>=0.4.27; extra == 'magic'
Provides-Extra: mq
Requires-Dist: pika>=1.3.2; extra == 'mq'
Provides-Extra: s3
Requires-Dist: boto3>=1.40.21; extra == 's3'
